selfdelete/__init__.py
selfdelete/policy.py
TracSelfDelete-2.1.dist-info/COPYING
TracSelfDelete-2.1.dist-info/METADATA
TracSelfDelete-2.1.dist-info/WHEEL
TracSelfDelete-2.1.dist-info/entry_points.txt
TracSelfDelete-2.1.dist-info/top_level.txt
TracSelfDelete-2.1.dist-info/RECORD
