Metadata-Version: 2.1
Name: TracSelfDelete
Version: 2.1
Summary: Permissions policy that allows users to delete wiki pages and attachments that they created.
Home-page: https://trac-hacks.org/wiki/SelfDeletePlugin
Author: Ryan J Ollos
Author-email: ryan.j.ollos@gmail.com
License: BSD
Keywords: trac plugin wiki attachment delete
Platform: UNKNOWN
Classifier: Framework :: Trac
